eurydice_test_framework/__init__.py
eurydice_test_framework/__main__.py
eurydice_test_framework/core/__init__.py
eurydice_test_framework/core/database/__init__.py
eurydice_test_framework/core/database/tables/__init__.py
eurydice_test_framework/core/database/tables/tests_run.py
eurydice_test_framework/core/management/__init__.py
eurydice_test_framework/core/management/command_line_handler.py
eurydice_test_framework/core/management/directory_handler.py
eurydice_test_framework/core/management/tests_handler.py
eurydice_test_framework/core/management/command_groups/__init__.py
eurydice_test_framework/core/management/command_groups/base_group.py
eurydice_test_framework/core/management/command_groups/database.py
eurydice_test_framework/core/management/command_groups/project.py
eurydice_test_framework/core/management/command_groups/report.py
eurydice_test_framework/core/management/command_groups/service.py
eurydice_test_framework/core/management/command_groups/tests.py
eurydice_test_framework/core/management/errors/__init__.py
eurydice_test_framework/core/management/errors/command_parse_exception.py
eurydice_test_framework/core/wrappers/__init__.py
eurydice_test_framework/core/wrappers/docker.py
eurydice_test_framework/src/__init__.py
eurydice_test_framework/src/base_api.py
eurydice_test_framework/src/config.py
eurydice_test_framework/src/database/__init__.py
eurydice_test_framework/src/database/handler.py
eurydice_test_framework/templates/__init__.py
eurydice_test_framework/templates/api.py
eurydice_test_framework/templates/config_yaml.py
eurydice_test_framework/templates/dashboard_json.py
eurydice_test_framework/templates/dashboard_yaml.py
eurydice_test_framework/templates/datasource.py
eurydice_test_framework/templates/docker_compose_yaml.py
eurydice_test_framework/templates/env.py
eurydice_test_framework/templates/test.py
eurydice_test_framework-0.1.1.dist-info/LICENSE
eurydice_test_framework-0.1.1.dist-info/METADATA
eurydice_test_framework-0.1.1.dist-info/WHEEL
eurydice_test_framework-0.1.1.dist-info/entry_points.txt
eurydice_test_framework-0.1.1.dist-info/top_level.txt
eurydice_test_framework-0.1.1.dist-info/RECORD
