Metadata-Version: 2.1
Name: eurydice_test_framework
Version: 0.1.1
Project-URL: Homepage, https://github.com/korneyaitmatoff/eurydice_test_framework
Requires-Python: >=3.11
License-File: LICENSE
Requires-Dist: numpy
Requires-Dist: pytest
Requires-Dist: SQLAlchemy
Requires-Dist: psycopg2
Requires-Dist: docker
Requires-Dist: loguru
